LICENSE
README.md
pyproject.toml
setup.py
planet_utils/__init__.py
planet_utils/bands.py
planet_utils/metadata.py
planet_utils/plot.py
planet_utils/read.py
planet_utils.egg-info/PKG-INFO
planet_utils.egg-info/SOURCES.txt
planet_utils.egg-info/dependency_links.txt
planet_utils.egg-info/requires.txt
planet_utils.egg-info/top_level.txt