Metadata-Version: 2.1
Name: planet-utils
Version: 0.0.4
Summary: The planetscope package is a tool specifically designed to read and plot data from the PlanetScope satellite imaging system.
Home-page: https://github.com/NASA-IMPACT/planet_utils
Download-URL: https://github.com/NASA-IMPACT/planet_utils/archive/refs/tags/0.0.3.tar.gz
Author: Ankur Kumar
Author-email: ankurk017@gmail.com
License: MIT
Keywords: planet,utils,smallsat,nasa,nasaimpact,planetscope
Platform: UNKNOWN
License-File: LICENSE
